.gitignore
LICENSE
MANIFEST.in
NOTICE
README.rst
THANKS
setup.py
examples/.hello.py.swo
examples/_sendfile.py
examples/amqp.py
examples/hello.py
examples/hello_pool.py
examples/multiworker.py
examples/multiworker2.py
examples/serve_file.py
examples/tcp_hello.py
examples/static/hello.html
examples/static/index.html
examples/static/images/gunicorn.png
examples/static/images/large_gunicorn.png
examples/static/images/logo.png
pistil/__init__.py
pistil/arbiter.py
pistil/errors.py
pistil/pidfile.py
pistil/pool.py
pistil/util.py
pistil/worker.py
pistil/workertmp.py
pistil.egg-info/PKG-INFO
pistil.egg-info/SOURCES.txt
pistil.egg-info/dependency_links.txt
pistil.egg-info/not-zip-safe
pistil.egg-info/top_level.txt
pistil/tcp/__init__.py
pistil/tcp/arbiter.py
pistil/tcp/gevent_worker.py
pistil/tcp/sock.py
pistil/tcp/sync_worker.py