Metadata-Version: 1.0
Name: pistil
Version: 0.2.0
Summary: Multiprocessing toolkit
Home-page: http://github.com/meebo/pistil
Author: Benoit Chesneau
Author-email: benoitc@e-engura.com
License: MIT
Platform: UNKNOWN
Classifier: Development Status :: 4 - Beta
Classifier: Environment :: Other Environment
Classifier: Intended Audience :: Developers
Classifier: License :: OSI Approved :: MIT License
Classifier: Operating System :: MacOS :: MacOS X
Classifier: Operating System :: POSIX
Classifier: Programming Language :: Python
Classifier: Topic :: Internet
Classifier: Topic :: Utilities
Classifier: Topic :: Software Development :: Libraries :: Python Modules
